cadctap/__init__.py
cadctap/core.py
cadctap/version.py
cadctap/tests/__init__.py
cadctap/tests/test_core.py
cadctap/tests/data/createTable.vosi
cadctap/tests/data/db_schema.xml
cadctap/tests/data/example_query.sql
cadctap/tests/data/help.txt
cadctap/tests/data/help_create.txt
cadctap/tests/data/help_delete.txt
cadctap/tests/data/help_index.txt
cadctap/tests/data/help_load.txt
cadctap/tests/data/help_permission.txt
cadctap/tests/data/help_permission_39.txt
cadctap/tests/data/help_query.txt
cadctap/tests/data/help_schema.txt
cadctap/tests/data/loadTable.txt
cadctap/tests/data/table_schema.xml
cadctap/tests/data/votable.xml
cadctap-0.9.11.dist-info/LICENSE
cadctap-0.9.11.dist-info/METADATA
cadctap-0.9.11.dist-info/WHEEL
cadctap-0.9.11.dist-info/entry_points.txt
cadctap-0.9.11.dist-info/top_level.txt
cadctap-0.9.11.dist-info/RECORD
