Metadata-Version: 2.1
Name: cadctap
Version: 0.9.11
Summary: Client for accessing data at the Canadian Astronomy Data Centre
Home-page: http://www.cadc-ccda.hia-iha.nrc-cnrc.gc.ca/
Author: Canadian Astronomy Data Centre
Author-email: cadc@nrc-cnrc.gc.ca
License: AGPLv3
Classifier: Natural Language :: English
Classifier: License :: OSI Approved :: GNU Affero General Public License v3
Classifier: Programming Language :: Python
Classifier: Programming Language :: Python :: 3
Requires-Python: >=3.7, <4
License-File: LICENSE
Requires-Dist: cadcutils (>=1.5)
Requires-Dist: clint (>=0.5.1)
Requires-Dist: requests (>=2.18)
Requires-Dist: requests-toolbelt (>=0.8.0)
Provides-Extra: test
Requires-Dist: pytest ; extra == 'test'
Requires-Dist: pytest-cov (>=2.5.1) ; extra == 'test'
Requires-Dist: flake8 (>=3.4.1) ; extra == 'test'
Requires-Dist: funcsigs (==1.0.2) ; extra == 'test'
Requires-Dist: mock (>=2.0.0) ; extra == 'test'
Requires-Dist: xml-compare (>=1.0.5) ; extra == 'test'
